dataviewer/__init__.py
dataviewer/models.py
dataviewer/py.typed
dataviewer/services.py
django_anchor_modeling/__init__.py
django_anchor_modeling/fields.py
django_anchor_modeling/managers.py
django_anchor_modeling/models.py
django_anchor_modeling/py.typed
metadata/__init__.py
metadata/models.py
metadata/py.typed
metadata/services.py
metadata/migrations/0001_initial.py
metadata/migrations/0002_datachangereason.py
metadata/migrations/__init__.py
django_anchor_modeling-0.0.7.dist-info/LICENSE
django_anchor_modeling-0.0.7.dist-info/METADATA
django_anchor_modeling-0.0.7.dist-info/WHEEL
django_anchor_modeling-0.0.7.dist-info/top_level.txt
django_anchor_modeling-0.0.7.dist-info/RECORD
