Metadata-Version: 2.1
Name: django-anchor-modeling
Version: 0.0.7
Summary: one line description about the project
Home-page: https://github.com/GreenDeploy-io/django-anchor-modeling
Author: author_name
Maintainer: maintainer_name
License: MIT
Project-URL: Changelog, https://github.com/GreenDeploy-io/django-anchor-modeling/blob/main/CHANGELOG.rst
Keywords: django
Classifier: Development Status :: 4 - Beta
Classifier: Environment :: Web Environment
Classifier: Framework :: Django
Classifier: Framework :: Django :: 4.2
Classifier: Intended Audience :: Developers
Classifier: License :: OSI Approved :: MIT License
Classifier: Natural Language :: English
Classifier: Operating System :: OS Independent
Classifier: Programming Language :: Python :: 3
Classifier: Programming Language :: Python :: 3 :: Only
Classifier: Programming Language :: Python :: 3.10
Classifier: Programming Language :: Python :: 3.11
Classifier: Programming Language :: Python :: 3.12
Classifier: Programming Language :: Python :: Implementation :: CPython
Classifier: Typing :: Typed
Requires-Python: >=3.10
License-File: LICENSE
Requires-Dist: Django >=4.2
